gql/cli.py
gql/config.py
gql/query_parser.py
gql/renderer_dataclasses.py
gql/utils_codegen.py
gql/utils_schema.py
gql/clients/__init__.py
gql/clients/asyncio.py
gql/clients/sync.py
cfk_gql-6.0.dist-info/METADATA
cfk_gql-6.0.dist-info/WHEEL
cfk_gql-6.0.dist-info/entry_points.txt
cfk_gql-6.0.dist-info/top_level.txt
cfk_gql-6.0.dist-info/RECORD
